not_an_ssg/LICENSE
not_an_ssg/__init__.py
not_an_ssg/articles_css.css
not_an_ssg/build.py
not_an_ssg/demo.py
not_an_ssg/demo_comprehensive.md
not_an_ssg/frontmatter.py
not_an_ssg/not_an_ssg.py
not_an_ssg/r2_bucket.py
not_an_ssg/setup.py
not_an_ssg/ui_components.py
not_an_ssg-2.2.3.dist-info/METADATA
not_an_ssg-2.2.3.dist-info/WHEEL
not_an_ssg-2.2.3.dist-info/entry_points.txt
not_an_ssg-2.2.3.dist-info/top_level.txt
not_an_ssg-2.2.3.dist-info/RECORD
