Metadata-Version: 2.4
Name: not_an_ssg
Version: 2.2.3
Home-page: https://github.com/mebinthattil/Not-An-SSG
Author: Mebin
Author-email: mail@mebin.in
Requires-Dist: boto3>=1.37.10
Requires-Dist: markdown>=3.7
Requires-Dist: pygments>=2.18.0
Requires-Dist: python-dotenv>=1.1.1
Requires-Dist: PyYAML>=6.0
Requires-Dist: importlib-resources>=1.3.0; python_version < "3.9"
Dynamic: author
Dynamic: author-email
Dynamic: description
Dynamic: description-content-type
Dynamic: home-page
Dynamic: requires-dist
